lariat/__init__.py
lariat/version.py
lariat/bootstrap/__init__.py
lariat/bootstrap/sitecustomize.py
lariat/config/__init__.py
lariat/config/config.py
lariat/config/defaults.py
lariat/metrics/__init__.py
lariat/metrics/collector.py
lariat/patch/__init__.py
lariat/patch/flask.py
lariat/patch/main.py
lariat/patch/mlflow.py
lariat/patch/pandas.py
lariat/patch/pytorch.py
lariat/patch/sklearn.py
lariat/patch/sqlalchemy.py
lariat/patch/statsd_config.py
lariat/patch/subprocess.py
lariat/patch/util.py
lariat/readers/__init__.py
lariat/readers/directory.py
lariat/scripts/lariat_run.py
lariat/templates/trace-bundle.html
lariat/tracing/__init__.py
lariat/tracing/client.py
lariat/tracing/config.py
lariat/tracing/headless_extension.py
lariat/tracing/local_context.py
lariat/tracing/transport.py
lariat_run-0.1.103.dist-info/LICENSE
lariat_run-0.1.103.dist-info/METADATA
lariat_run-0.1.103.dist-info/WHEEL
lariat_run-0.1.103.dist-info/entry_points.txt
lariat_run-0.1.103.dist-info/top_level.txt
lariat_run-0.1.103.dist-info/RECORD
