Metadata-Version: 2.1
Name: lariat-run
Version: 0.1.103
Summary: UNKNOWN
Home-page: UNKNOWN
Author: UNKNOWN
Author-email: UNKNOWN
License: Creative Commons Attribution-Noncommercial-Share Alike license
Platform: UNKNOWN
Requires-Dist: statsd (==3.3.0)
Requires-Dist: psutil (==5.7.0)
